zet/__init__.py
zet/api.py
zet/app.css
zet/app.py
zet/cli.py
zet/config.py
zet/decorators.py
zet/entities.py
zet/http.py
zet/output.py
zet/widgets.py
zet/panes/__init__.py
zet/panes/news.py
zet/panes/routes.py
zet/panes/stops.py
mojzet-1.3.0.dist-info/METADATA
mojzet-1.3.0.dist-info/WHEEL
mojzet-1.3.0.dist-info/entry_points.txt
mojzet-1.3.0.dist-info/licenses/LICENSE
mojzet-1.3.0.dist-info/RECORD
