Metadata-Version: 2.4
Name: mojzet
Version: 1.3.0
Summary: Access ZET trips and time tables from the comfort of your terminal
Author-email: Ivan Habunek <ivan@habunek.com>
License:                     GNU GENERAL PUBLIC LICENSE
License-File: LICENSE
Requires-Python: >=3.12
Requires-Dist: aiohttp[speedups]>=3.11
Requires-Dist: click>=8.1.8
Requires-Dist: python-dateutil>=2.9.0.post0
Requires-Dist: textual>=3.1.1
Requires-Dist: tomlkit>=0.13.3
